gitRemoteAws/__init__.py
gitRemoteAws/botoman.py
gitRemoteAws/cli_cloudtrail.py
gitRemoteAws/cli_cw.py
gitRemoteAws/cli_ec2.py
gitRemoteAws/cli_sns.py
gitRemoteAws/dotman.py
gitRemoteAws/pull_cloudtrail_lookupEvents.py
gitRemoteAws/pull_cloudwatch.py
gitRemoteAws/pull_ec2.py
gitRemoteAws/pull_sns.py
gitRemoteAws/utils.py
git_remote_aws-0.5.4.dist-info/LICENSE
git_remote_aws-0.5.4.dist-info/METADATA
git_remote_aws-0.5.4.dist-info/WHEEL
git_remote_aws-0.5.4.dist-info/entry_points.txt
git_remote_aws-0.5.4.dist-info/top_level.txt
git_remote_aws-0.5.4.dist-info/RECORD
